{
  "infer_schema": [
    [
      {
        "#docs": 1000,
        "$schema": "http://json-schema.org/draft-06/schema",
        "Flavor": "",
        "properties": {
          "baopp": {
            "#docs": [
              984,
              16
            ],
            "%docs": [
              98.4,
              1.6
            ],
            "nestingDepth": 0,
            "samples": [
              [
                0.16,
                0.25,
                0.27,
                0.32,
                0.33
              ],
              [
                ""
              ]
            ],
            "type": [
              "number",
              "string"
            ]
          },
          "bb": {
            "#docs": 1000,
            "%docs": 100,
            "nestingDepth": 0,
            "samples": [
              1,
              5,
              7,
              10,
              29
            ],
            "type": "number"
          },
          "bfp": {
            "#docs": [
              997,
              3
            ],
            "%docs": [
              99.7,
              0.3
            ],
            "nestingDepth": 0,
            "samples": [
              [
                0,
                9,
                22,
                402,
                615
              ],
              [
                ""
              ]
            ],
            "type": [
              "number",
              "string"
            ]
          },
          "bk": {
            "#docs": 1000,
            "%docs": 100,
            "nestingDepth": 0,
            "samples": [
              0,
              1,
              2,
              4,
              5
            ],
            "type": "number"
          },
          "cg": {
            "#docs": 1000,
            "%docs": 100,
            "nestingDepth": 0,
            "samples": [
              0,
              1,
              2,
              9,
              13
            ],
            "type": "number"
          },
          "er": {
            "#docs": 1000,
            "%docs": 100,
            "nestingDepth": 0,
            "samples": [
              1,
              4,
              11,
              17,
              69
            ],
            "type": "number"
          },
          "era": {
            "#docs": [
              998,
              2
            ],
            "%docs": [
              99.8,
              0.2
            ],
            "nestingDepth": 0,
            "samples": [
              [
                3,
                4.5,
                5.1,
                7.57,
                9
              ],
              [
                ""
              ]
            ],
            "type": [
              "number",
              "string"
            ]
          },
          "g": {
            "#docs": 1000,
            "%docs": 100,
            "nestingDepth": 0,
            "samples": [
              1,
              2,
              3,
              7,
              10
            ],
            "type": "number"
          },
          "g_idp": {
            "#docs": [
              11,
              989
            ],
            "%docs": [
              1.1,
              98.9
            ],
            "nestingDepth": 0,
            "samples": [
              [
                0,
                1,
                3,
                5,
                12
              ],
              [
                ""
              ]
            ],
            "type": [
              "number",
              "string"
            ]
          },
          "gf": {
            "#docs": [
              997,
              3
            ],
            "%docs": [
              99.7,
              0.3
            ],
            "nestingDepth": 0,
            "samples": [
              [
                0,
                1,
                2,
                3,
                4
              ],
              [
                ""
              ]
            ],
            "type": [
              "number",
              "string"
            ]
          },
          "gs": {
            "#docs": 1000,
            "%docs": 100,
            "nestingDepth": 0,
            "samples": [
              0,
              1,
              3,
              10,
              17
            ],
            "type": "number"
          },
          "h": {
            "#docs": 1000,
            "%docs": 100,
            "nestingDepth": 0,
            "samples": [
              2,
              4,
              15,
              41,
              123
            ],
            "type": "number"
          },
          "hbp": {
            "#docs": [
              994,
              6
            ],
            "%docs": [
              99.4,
              0.6
            ],
            "nestingDepth": 0,
            "samples": [
              [
                0,
                1,
                2,
                3,
                6
              ],
              [
                ""
              ]
            ],
            "type": [
              "number",
              "string"
            ]
          },
          "hr": {
            "#docs": 1000,
            "%docs": 100,
            "nestingDepth": 0,
            "samples": [
              0,
              1,
              2,
              3,
              8
            ],
            "type": "number"
          },
          "ibb": {
            "#docs": [
              443,
              557
            ],
            "%docs": [
              44.3,
              55.7
            ],
            "nestingDepth": 0,
            "samples": [
              [
                0,
                1,
                2,
                3,
                5
              ],
              [
                ""
              ]
            ],
            "type": [
              "number",
              "string"
            ]
          },
          "ipouts": {
            "#docs": 1000,
            "%docs": 100,
            "nestingDepth": 0,
            "samples": [
              6,
              12,
              33,
              90,
              246
            ],
            "type": "number"
          },
          "l": {
            "#docs": 1000,
            "%docs": 100,
            "nestingDepth": 0,
            "samples": [
              0,
              1,
              2,
              9,
              10
            ],
            "type": "number"
          },
          "league_id": {
            "#docs": 1000,
            "%docs": 100,
            "nestingDepth": 0,
            "samples": [
              "AA",
              "AL",
              "FL",
              "NL",
              "PL"
            ],
            "type": "string"
          },
          "player_id": {
            "#docs": 1000,
            "%docs": 100,
            "nestingDepth": 0,
            "samples": [
              "harribu02",
              "horneja01",
              "mckeero01",
              "murphed01",
              "phillbi02"
            ],
            "type": "string"
          },
          "r": {
            "#docs": 1000,
            "%docs": 100,
            "nestingDepth": 0,
            "samples": [
              1,
              4,
              12,
              23,
              97
            ],
            "type": "number"
          },
          "sf": {
            "#docs": [
              215,
              785
            ],
            "%docs": [
              21.5,
              78.5
            ],
            "nestingDepth": 0,
            "samples": [
              [
                0,
                1,
                2,
                6,
                7
              ],
              [
                ""
              ]
            ],
            "type": [
              "number",
              "string"
            ]
          },
          "sh": {
            "#docs": [
              215,
              785
            ],
            "%docs": [
              21.5,
              78.5
            ],
            "nestingDepth": 0,
            "samples": [
              [
                0,
                1,
                3,
                7,
                10
              ],
              [
                ""
              ]
            ],
            "type": [
              "number",
              "string"
            ]
          },
          "sho": {
            "#docs": 1000,
            "%docs": 100,
            "nestingDepth": 0,
            "samples": [
              0,
              1,
              2,
              3,
              6
            ],
            "type": "number"
          },
          "so": {
            "#docs": 1000,
            "%docs": 100,
            "nestingDepth": 0,
            "samples": [
              0,
              2,
              8,
              25,
              39
            ],
            "type": "number"
          },
          "stint": {
            "#docs": 1000,
            "%docs": 100,
            "nestingDepth": 0,
            "samples": [
              1,
              2,
              3
            ],
            "type": "number"
          },
          "sv": {
            "#docs": 1000,
            "%docs": 100,
            "nestingDepth": 0,
            "samples": [
              0,
              1,
              2,
              3,
              4
            ],
            "type": "number"
          },
          "team_id": {
            "#docs": 1000,
            "%docs": 100,
            "nestingDepth": 0,
            "samples": [
              "BLN",
              "CHN",
              "PHA",
              "PHI",
              "PIT"
            ],
            "type": "string"
          },
          "w": {
            "#docs": 1000,
            "%docs": 100,
            "nestingDepth": 0,
            "samples": [
              0,
              1,
              2,
              4,
              8
            ],
            "type": "number"
          },
          "wp": {
            "#docs": [
              997,
              3
            ],
            "%docs": [
              99.7,
              0.3
            ],
            "nestingDepth": 0,
            "samples": [
              [
                0,
                1,
                3,
                5,
                7
              ],
              [
                ""
              ]
            ],
            "type": [
              "number",
              "string"
            ]
          },
          "year": {
            "#docs": 1000,
            "%docs": 100,
            "nestingDepth": 0,
            "samples": [
              1890,
              1894,
              1898,
              1944,
              1951
            ],
            "type": "number"
          },
          "~meta": {
            "#docs": 1000,
            "%docs": 100,
            "nestingDepth": 0,
            "properties": {
              "id": {
                "#docs": 1000,
                "%docs": 100,
                "nestingDepth": 1,
                "samples": [
                  "pitching::11976",
                  "pitching::13664",
                  "pitching::1499",
                  "pitching::1971",
                  "pitching::2459"
                ],
                "type": "string"
              }
            },
            "samples": [
              {
                "id": "pitching::11976"
              },
              {
                "id": "pitching::13664"
              },
              {
                "id": "pitching::1499"
              },
              {
                "id": "pitching::1971"
              },
              {
                "id": "pitching::2459"
              }
            ],
            "type": "object"
          }
        },
        "type": "object"
      }
    ]
  ],
  "sample_rows": [
    {
      "baopp": 0.28,
      "bb": 42,
      "bfp": 1207,
      "bk": 2,
      "cg": 13,
      "er": 126,
      "era": 4.02,
      "g": 51,
      "g_idp": "",
      "gf": 10,
      "gs": 37,
      "h": 331,
      "hbp": 4,
      "hr": 11,
      "ibb": "",
      "ipouts": 847,
      "l": 19,
      "league_id": "NL",
      "player_id": "derripa01",
      "r": 147,
      "sf": "",
      "sh": "",
      "sho": 2,
      "so": 121,
      "stint": 1,
      "sv": 5,
      "team_id": "CIN",
      "w": 19,
      "wp": 6,
      "year": 1936
    },
    {
      "baopp": 0.35,
      "bb": 2,
      "bfp": 35,
      "bk": 0,
      "cg": 0,
      "er": 3,
      "era": 3.38,
      "g": 1,
      "g_idp": "",
      "gf": 0,
      "gs": 1,
      "h": 11,
      "hbp": 1,
      "hr": 1,
      "ibb": "",
      "ipouts": 24,
      "l": 1,
      "league_id": "NL",
      "player_id": "dollar01",
      "r": 3,
      "sf": "",
      "sh": "",
      "sho": 0,
      "so": 2,
      "stint": 1,
      "sv": 0,
      "team_id": "BSN",
      "w": 0,
      "wp": 0,
      "year": 1936
    },
    {
      "baopp": 0.26,
      "bb": 15,
      "bfp": 67,
      "bk": 0,
      "cg": 1,
      "er": 10,
      "era": 6.59,
      "g": 2,
      "g_idp": "",
      "gf": 0,
      "gs": 2,
      "h": 14,
      "hbp": 0,
      "hr": 0,
      "ibb": "",
      "ipouts": 41,
      "l": 1,
      "league_id": "AL",
      "player_id": "zuberbi01",
      "r": 11,
      "sf": "",
      "sh": "",
      "sho": 0,
      "so": 5,
      "stint": 1,
      "sv": 0,
      "team_id": "CLE",
      "w": 1,
      "wp": 0,
      "year": 1936
    },
    {
      "baopp": 0.29,
      "bb": 79,
      "bfp": 1276,
      "bk": 0,
      "cg": 18,
      "er": 141,
      "era": 4.34,
      "g": 50,
      "g_idp": "",
      "gf": 12,
      "gs": 34,
      "h": 348,
      "hbp": 5,
      "hr": 16,
      "ibb": "",
      "ipouts": 877,
      "l": 18,
      "league_id": "NL",
      "player_id": "passecl01",
      "r": 158,
      "sf": "",
      "sh": "",
      "sho": 1,
      "so": 135,
      "stint": 1,
      "sv": 2,
      "team_id": "PHI",
      "w": 14,
      "wp": 0,
      "year": 1937
    },
    {
      "baopp": 0.25,
      "bb": 48,
      "bfp": 654,
      "bk": 1,
      "cg": 7,
      "er": 51,
      "era": 2.97,
      "g": 37,
      "g_idp": "",
      "gf": 11,
      "gs": 17,
      "h": 150,
      "hbp": 1,
      "hr": 2,
      "ibb": "",
      "ipouts": 463,
      "l": 13,
      "league_id": "NL",
      "player_id": "schotge01",
      "r": 69,
      "sf": "",
      "sh": "",
      "sho": 2,
      "so": 56,
      "stint": 1,
      "sv": 1,
      "team_id": "CIN",
      "w": 4,
      "wp": 4,
      "year": 1937
    }
  ]
}